AgentCrew/__init__.py
AgentCrew/app.py
AgentCrew/main.py
AgentCrew/main_docker.py
AgentCrew/assets/agentcrew_logo.png
AgentCrew/modules/__init__.py
AgentCrew/modules/a2a/__init__.py
AgentCrew/modules/a2a/adapters.py
AgentCrew/modules/a2a/agent_cards.py
AgentCrew/modules/a2a/errors.py
AgentCrew/modules/a2a/registry.py
AgentCrew/modules/a2a/server.py
AgentCrew/modules/a2a/task_manager.py
AgentCrew/modules/a2a/common/__init__.py
AgentCrew/modules/a2a/common/client/__init__.py
AgentCrew/modules/a2a/common/client/card_resolver.py
AgentCrew/modules/a2a/common/client/client.py
AgentCrew/modules/a2a/common/server/__init__.py
AgentCrew/modules/a2a/common/server/auth_middleware.py
AgentCrew/modules/a2a/common/server/task_manager.py
AgentCrew/modules/a2a/common/server/utils.py
AgentCrew/modules/agents/__init__.py
AgentCrew/modules/agents/base.py
AgentCrew/modules/agents/example.py
AgentCrew/modules/agents/local_agent.py
AgentCrew/modules/agents/manager.py
AgentCrew/modules/agents/remote_agent.py
AgentCrew/modules/agents/tools/__init__.py
AgentCrew/modules/agents/tools/ask.py
AgentCrew/modules/agents/tools/delegate.py
AgentCrew/modules/agents/tools/transfer.py
AgentCrew/modules/anthropic/__init__.py
AgentCrew/modules/anthropic/service.py
AgentCrew/modules/browser_automation/__init__.py
AgentCrew/modules/browser_automation/chrome_manager.py
AgentCrew/modules/browser_automation/element_extractor.py
AgentCrew/modules/browser_automation/js_loader.py
AgentCrew/modules/browser_automation/service.py
AgentCrew/modules/browser_automation/tool.py
AgentCrew/modules/browser_automation/js/click_element.js
AgentCrew/modules/browser_automation/js/draw_element_boxes.js
AgentCrew/modules/browser_automation/js/extract_clickable_elements.js
AgentCrew/modules/browser_automation/js/extract_elements_by_text.js
AgentCrew/modules/browser_automation/js/extract_input_elements.js
AgentCrew/modules/browser_automation/js/extract_scrollable_elements.js
agentcrew_ai-0.8.11.dist-info/licenses/LICENSE
agentcrew_ai-0.8.11.dist-info/METADATA
agentcrew_ai-0.8.11.dist-info/WHEEL
agentcrew_ai-0.8.11.dist-info/entry_points.txt
agentcrew_ai-0.8.11.dist-info/top_level.txt
agentcrew_ai-0.8.11.dist-info/RECORD
