Metadata-Version: 2.4
Name: agentcrew-ai
Version: 0.8.11
Summary: Multi-Agents Interactive Chat Tool
Author-email: Quy Truong <quy.truong@saigontechnology.com>
License-Expression: Apache-2.0
Project-URL: Homepage, https://github.com/daltonnyx/AgentCrew
Project-URL: Bug Tracker, https://github.com/daltonnyx/AgentCrew/issues
Classifier: Programming Language :: Python :: 3
Classifier: Operating System :: OS Independent
Classifier: Development Status :: 4 - Beta
Classifier: Intended Audience :: Developers
Classifier: Topic :: Software Development :: Libraries :: Python Modules
Classifier: Topic :: Scientific/Engineering :: Artificial Intelligence
Requires-Python: >=3.12
License-File: LICENSE
Requires-Dist: click
Requires-Dist: python-dotenv
Requires-Dist: anthropic
Requires-Dist: pytest
Requires-Dist: prompt-toolkit>=3.0.52
Requires-Dist: rich>=13.9.4
Requires-Dist: pyperclip>=1.9.0
Requires-Dist: tavily-python>=0.5.1
Requires-Dist: pillow>=11.0.0
Requires-Dist: groq>=0.18.0
Requires-Dist: chromadb>=1.0.0
Requires-Dist: openai>=1.65.2
Requires-Dist: mcp>=1.24.0
Requires-Dist: google-genai>=1.7.0
Requires-Dist: pyside6>=6.8.3
Requires-Dist: markdown>=3.7
Requires-Dist: tree-sitter-language-pack>=0.10.0
Requires-Dist: nest-asyncio>=1.6.0
Requires-Dist: voyageai>=0.3.2
Requires-Dist: numpy<2,>=1.24.4; python_version < "3.13" and sys_platform == "darwin"
Requires-Dist: pywin32; sys_platform == "win32"
Requires-Dist: pyobjc; sys_platform == "darwin"
Requires-Dist: a2a-sdk>=0.3.10
Requires-Dist: qtawesome>=1.4.0
Requires-Dist: xmltodict>=0.14.2
Requires-Dist: elevenlabs>=2.12.1
Requires-Dist: sounddevice>=0.5.2
Requires-Dist: soundfile>=0.13.1
Requires-Dist: jsonref>=1.1.0
Requires-Dist: pychromedevtools>=0.3.3
Requires-Dist: html-to-markdown>=2.9.1
Requires-Dist: pip-system-certs>=5.2
Requires-Dist: loguru>=0.7.3
Requires-Dist: jsonschema>=4.25.1
Requires-Dist: tomli-w>=1.2.0
Provides-Extra: cpu
Requires-Dist: torch>=2.8.0; extra == "cpu"
Requires-Dist: torchvision>=0.23.0; extra == "cpu"
Requires-Dist: torchaudio>=2.8.0; extra == "cpu"
Requires-Dist: docling>=2.26.0; extra == "cpu"
Provides-Extra: nvidia
Requires-Dist: torch>=2.8.0; extra == "nvidia"
Requires-Dist: torchvision>=0.23.0; extra == "nvidia"
Requires-Dist: torchaudio>=2.8.0; extra == "nvidia"
Requires-Dist: docling>=2.26.0; extra == "nvidia"
Dynamic: license-file
